dinject/__init__.py
dinject/__main__.py
dinject/cli.py
dinject/execute.py
dinject/inject.py
dinject/parser.py
dinject/py.typed
dinject/enums/__init__.py
dinject/enums/content.py
dinject/enums/host.py
dinject/enums/py.typed
dinject/enums/range.py
dinject/exceptions/__init__.py
dinject/exceptions/dinject.py
dinject/exceptions/instruction.py
dinject/exceptions/py.typed
dinject/executors/__init__.py
dinject/executors/bash.py
dinject/executors/py.typed
dinject/executors/python.py
dinject/types/__init__.py
dinject/types/executor.py
dinject/types/instruction.py
dinject/types/parser_options.py
dinject/types/py.typed
dinject/version/VERSION
dinject/version/__init__.py
dinject/version/py.typed
dinject-1.3.0.dist-info/LICENSE
dinject-1.3.0.dist-info/METADATA
dinject-1.3.0.dist-info/WHEEL
dinject-1.3.0.dist-info/entry_points.txt
dinject-1.3.0.dist-info/top_level.txt
dinject-1.3.0.dist-info/RECORD
