Metadata-Version: 2.1
Name: dinject
Version: 1.3.0
Summary: Executes and injects code in Markdown documents
Home-page: https://github.com/cariad/dinject
Author: Cariad Eccleston
Author-email: cariad@cariad.earth
License: MIT
Platform: UNKNOWN
Classifier: Development Status :: 5 - Production/Stable
Classifier: Environment :: Console
Classifier: License :: OSI Approved :: MIT License
Classifier: Natural Language :: English
Classifier: Operating System :: OS Independent
Classifier: Programming Language :: Python :: 3 :: Only
Classifier: Programming Language :: Python :: 3.10
Classifier: Programming Language :: Python :: 3.8
Classifier: Programming Language :: Python :: 3.9
Classifier: Topic :: Utilities
Classifier: Typing :: Typed
Requires-Python: >=3.8
License-File: LICENSE
Requires-Dist: comprehemd (~=1.0)
Requires-Dist: naughtty (~=1.0)
Requires-Dist: thtml (~=1.0.5)
